deepdiff_yb/__init__.py
deepdiff_yb/contenthash.py
deepdiff_yb/diff.py
deepdiff_yb/helper.py
deepdiff_yb/search.py
deepdiff_yb-0.1.0.dist-info/LICENSE
deepdiff_yb-0.1.0.dist-info/WHEEL
deepdiff_yb-0.1.0.dist-info/METADATA
deepdiff_yb-0.1.0.dist-info/RECORD
